pytest_auto_parametrize.py
pytest_auto_parametrize-0.1.0.dist-info/DESCRIPTION.rst
pytest_auto_parametrize-0.1.0.dist-info/METADATA
pytest_auto_parametrize-0.1.0.dist-info/RECORD
pytest_auto_parametrize-0.1.0.dist-info/WHEEL
pytest_auto_parametrize-0.1.0.dist-info/entry_points.txt
pytest_auto_parametrize-0.1.0.dist-info/metadata.json
pytest_auto_parametrize-0.1.0.dist-info/top_level.txt
pytest_auto_parametrize-0.1.0.dist-info/zip-safe
