Metadata-Version: 2.0
Name: pytest-auto-parametrize
Version: 0.1.0
Summary: pytest plugin: avoid repeating arguments in parametrize
Home-page: https://github.com/mgeier/pytest-auto-parametrize
Author: Matthias Geier
Author-email: Matthias.Geier@gmail.com
License: MIT
Keywords: parametrized,testing
Platform: any
Classifier: Framework :: Pytest
Classifier: Development Status :: 3 - Alpha
Classifier: License :: OSI Approved :: MIT License
Classifier: Operating System :: OS Independent
Classifier: Programming Language :: Python
Classifier: Programming Language :: Python :: 2
Classifier: Programming Language :: Python :: 3
Classifier: Intended Audience :: Developers
Classifier: Topic :: Software Development :: Testing
